climate_risk
