Metadata-Version: 2.1
Name: esg-riskmon-climaterisk
Version: 0.0.5
Summary: Package for Climate Risk Analytics.
Home-page: https://github.com/NBIM/climate_risk
Download-URL: https://github.com/NBIM/climate_risk/archive/refs/tags/v0.0.5.tar.gz
Author: Ginni Berti-Mei
Author-email: ginevra.berti.mei@nbim.no
License: MIT
Classifier: Development Status :: 3 - Alpha
Classifier: Topic :: Software Development :: Build Tools
Classifier: License :: OSI Approved :: MIT License
Classifier: Programming Language :: Python :: 3
Classifier: Programming Language :: Python :: 3.6
Classifier: Programming Language :: Python :: 3.7
Classifier: Programming Language :: Python :: 3.8
Classifier: Programming Language :: Python :: 3.9
License-File: LICENSE.txt
